{"trial_id": "0008", "hyperparameters": {"space": [{"class_name": "Int", "config": {"name": "units1", "default": null, "conditions": [], "min_value": 32, "max_value": 128, "step": 32, "sampling": "linear"}}, {"class_name": "Int", "config": {"name": "units2", "default": null, "conditions": [], "min_value": 32, "max_value": 128, "step": 32, "sampling": "linear"}}, {"class_name": "Int", "config": {"name": "units3", "default": null, "conditions": [], "min_value": 32, "max_value": 128, "step": 32, "sampling": "linear"}}, {"class_name": "Float", "config": {"name": "learning_rate", "default": 0.0001, "conditions": [], "min_value": 0.0001, "max_value": 0.01, "step": null, "sampling": "log"}}], "values": {"units1": 64, "units2": 128, "units3": 32, "learning_rate": 0.0011842572503478156, "tuner/epochs": 4, "tuner/initial_epoch": 0, "tuner/bracket": 2, "tuner/round": 0}}, "metrics": {"metrics": {"bicyclefreq_output_loss": {"direction": "min", "observations": [{"value": [3451.655517578125], "step": 2}]}, "bicyclefreq_output_mean_squared_error": {"direction": "min", "observations": [{"value": [3452.13427734375], "step": 2}]}, "loss": {"direction": "min", "observations": [{"value": [25704.78125], "step": 2}]}, "main_mode_output_accuracy": {"direction": "min", "observations": [{"value": [0.5722805857658386], "step": 2}]}, "main_mode_output_categorical_crossentropy": {"direction": "min", "observations": [{"value": [15.497669219970703], "step": 2}]}, "main_mode_output_loss": {"direction": "min", "observations": [{"value": [15.498422622680664], "step": 2}]}, "ordbusfreq_output_loss": {"direction": "min", "observations": [{"value": [7647.08056640625], "step": 2}]}, "ordbusfreq_output_mean_squared_error": {"direction": "min", "observations": [{"value": [7647.8896484375], "step": 2}]}, "trip_dis_output_loss": {"direction": "min", "observations": [{"value": [1786.5390625], "step": 2}]}, "trip_dis_output_mean_squared_error": {"direction": "min", "observations": [{"value": [1786.772216796875], "step": 2}]}, "walkfreq_output_loss": {"direction": "min", "observations": [{"value": [12802.0595703125], "step": 2}]}, "walkfreq_output_mean_squared_error": {"direction": "min", "observations": [{"value": [12802.4951171875], "step": 2}]}, "val_bicyclefreq_output_loss": {"direction": "min", "observations": [{"value": [3345.100830078125], "step": 2}]}, "val_bicyclefreq_output_mean_squared_error": {"direction": "min", "observations": [{"value": [3344.95703125], "step": 2}]}, "val_loss": {"direction": "min", "observations": [{"value": [24819.96875], "step": 2}]}, "val_main_mode_output_accuracy": {"direction": "max", "observations": [{"value": [0.7488434314727783], "step": 2}]}, "val_main_mode_output_categorical_crossentropy": {"direction": "min", "observations": [{"value": [19.632568359375], "step": 2}]}, "val_main_mode_output_loss": {"direction": "min", "observations": [{"value": [19.625070571899414], "step": 2}]}, "val_ordbusfreq_output_loss": {"direction": "min", "observations": [{"value": [7316.17822265625], "step": 2}]}, "val_ordbusfreq_output_mean_squared_error": {"direction": "min", "observations": [{"value": [7315.8935546875], "step": 2}]}, "val_trip_dis_output_loss": {"direction": "min", "observations": [{"value": [1416.412841796875], "step": 2}]}, "val_trip_dis_output_mean_squared_error": {"direction": "min", "observations": [{"value": [1417.01318359375], "step": 2}]}, "val_walkfreq_output_loss": {"direction": "min", "observations": [{"value": [12724.4658203125], "step": 2}]}, "val_walkfreq_output_mean_squared_error": {"direction": "min", "observations": [{"value": [12722.4794921875], "step": 2}]}}}, "score": 0.7488434314727783, "best_step": 2, "status": "COMPLETED", "message": null}