{"trial_id": "0003", "hyperparameters": {"space": [{"class_name": "Int", "config": {"name": "units1", "default": null, "conditions": [], "min_value": 32, "max_value": 128, "step": 32, "sampling": "linear"}}, {"class_name": "Int", "config": {"name": "units2", "default": null, "conditions": [], "min_value": 32, "max_value": 128, "step": 32, "sampling": "linear"}}, {"class_name": "Int", "config": {"name": "units3", "default": null, "conditions": [], "min_value": 32, "max_value": 128, "step": 32, "sampling": "linear"}}, {"class_name": "Float", "config": {"name": "learning_rate", "default": 0.0001, "conditions": [], "min_value": 0.0001, "max_value": 0.01, "step": null, "sampling": "log"}}], "values": {"units1": 32, "units2": 32, "units3": 96, "learning_rate": 0.00520665224551133, "tuner/epochs": 4, "tuner/initial_epoch": 0, "tuner/bracket": 2, "tuner/round": 0}}, "metrics": {"metrics": {"bicyclefreq_output_loss": {"direction": "min", "observations": [{"value": [2956.79248046875], "step": 1}]}, "bicyclefreq_output_mean_squared_error": {"direction": "min", "observations": [{"value": [2957.2900390625], "step": 1}]}, "loss": {"direction": "min", "observations": [{"value": [24262.158203125], "step": 1}]}, "main_mode_output_accuracy": {"direction": "min", "observations": [{"value": [0.6086647510528564], "step": 1}]}, "main_mode_output_categorical_crossentropy": {"direction": "min", "observations": [{"value": [4.876462459564209], "step": 1}]}, "main_mode_output_loss": {"direction": "min", "observations": [{"value": [4.876366138458252], "step": 1}]}, "ordbusfreq_output_loss": {"direction": "min", "observations": [{"value": [7217.9423828125], "step": 1}]}, "ordbusfreq_output_mean_squared_error": {"direction": "min", "observations": [{"value": [7218.5009765625], "step": 1}]}, "trip_dis_output_loss": {"direction": "min", "observations": [{"value": [1450.6173095703125], "step": 1}]}, "trip_dis_output_mean_squared_error": {"direction": "min", "observations": [{"value": [1450.7850341796875], "step": 1}]}, "walkfreq_output_loss": {"direction": "min", "observations": [{"value": [12630.291015625], "step": 1}]}, "walkfreq_output_mean_squared_error": {"direction": "min", "observations": [{"value": [12630.6748046875], "step": 1}]}, "val_bicyclefreq_output_loss": {"direction": "min", "observations": [{"value": [2871.990234375], "step": 1}]}, "val_bicyclefreq_output_mean_squared_error": {"direction": "min", "observations": [{"value": [2871.718994140625], "step": 1}]}, "val_loss": {"direction": "min", "observations": [{"value": [24048.107421875], "step": 1}]}, "val_main_mode_output_accuracy": {"direction": "max", "observations": [{"value": [0.7488434314727783], "step": 1}]}, "val_main_mode_output_categorical_crossentropy": {"direction": "min", "observations": [{"value": [3.6512598991394043], "step": 1}]}, "val_main_mode_output_loss": {"direction": "min", "observations": [{"value": [3.6511688232421875], "step": 1}]}, "val_ordbusfreq_output_loss": {"direction": "min", "observations": [{"value": [7152.80419921875], "step": 1}]}, "val_ordbusfreq_output_mean_squared_error": {"direction": "min", "observations": [{"value": [7152.6328125], "step": 1}]}, "val_trip_dis_output_loss": {"direction": "min", "observations": [{"value": [1389.6409912109375], "step": 1}]}, "val_trip_dis_output_mean_squared_error": {"direction": "min", "observations": [{"value": [1390.194580078125], "step": 1}]}, "val_walkfreq_output_loss": {"direction": "min", "observations": [{"value": [12631.7490234375], "step": 1}]}, "val_walkfreq_output_mean_squared_error": {"direction": "min", "observations": [{"value": [12629.9091796875], "step": 1}]}}}, "score": 0.7488434314727783, "best_step": 1, "status": "COMPLETED", "message": null}